util_hj3415/__init__.py
util_hj3415/noti.py
util_hj3415/telegram_test.py
util_hj3415/utils.py
util_hj3415-1.1.3.dist-info/METADATA
util_hj3415-1.1.3.dist-info/WHEEL
util_hj3415-1.1.3.dist-info/licenses/LICENSE
util_hj3415-1.1.3.dist-info/RECORD
