Metadata-Version: 2.1
Name: util_hj3415
Version: 1.1.3
Summary: The collection of utility functions for hj3415
Project-URL: Homepage, https://pypi.org/project/util_hj3415/
Project-URL: Bug Tracker, https://pypi.org/project/util_hj3415/
Author-email: Hyungjin Kim <hj3415@gmail.com>
License-File: LICENSE
Classifier: License :: OSI Approved :: MIT License
Classifier: Operating System :: OS Independent
Classifier: Programming Language :: Python :: 3
Requires-Python: >=3.7
Requires-Dist: beautifulsoup4>=4.12.2
Requires-Dist: pymongo>=4.6.0
Requires-Dist: python-telegram-bot>=20.6
Requires-Dist: requests>=2.31.0
Requires-Dist: selenium>=4.15.2
Requires-Dist: webdriver-manager>=4.0.1
